{
  "id": "",
  "name": "",
  "font_family": "iconfont",
  "css_prefix_text": "icon-",
  "description": "",
  "glyphs": [
    {
      "icon_id": "11372639",
      "name": "爱心",
      "font_class": "aixin",
      "unicode": "e8ab",
      "unicode_decimal": 59563
    },
    {
      "icon_id": "11372640",
      "name": "编辑",
      "font_class": "bianji",
      "unicode": "e8ac",
      "unicode_decimal": 59564
    },
    {
      "icon_id": "11372643",
      "name": "安全",
      "font_class": "anquan",
      "unicode": "e8ad",
      "unicode_decimal": 59565
    },
    {
      "icon_id": "11372647",
      "name": "创作",
      "font_class": "chuangzuo",
      "unicode": "e8ae",
      "unicode_decimal": 59566
    },
    {
      "icon_id": "11372648",
      "name": "成功",
      "font_class": "chenggong",
      "unicode": "e8af",
      "unicode_decimal": 59567
    },
    {
      "icon_id": "11372652",
      "name": "定位",
      "font_class": "dingwei",
      "unicode": "e8b0",
      "unicode_decimal": 59568
    },
    {
      "icon_id": "11372658",
      "name": "订单",
      "font_class": "dingdan",
      "unicode": "e8b1",
      "unicode_decimal": 59569
    },
    {
      "icon_id": "11372661",
      "name": "发现",
      "font_class": "faxian",
      "unicode": "e8b2",
      "unicode_decimal": 59570
    },
    {
      "icon_id": "11372665",
      "name": "复制",
      "font_class": "fuzhi",
      "unicode": "e8b3",
      "unicode_decimal": 59571
    },
    {
      "icon_id": "11372666",
      "name": "分享",
      "font_class": "fenxiang",
      "unicode": "e8b4",
      "unicode_decimal": 59572
    },
    {
      "icon_id": "11372667",
      "name": "话题符号",
      "font_class": "huatifuhao",
      "unicode": "e8b5",
      "unicode_decimal": 59573
    },
    {
      "icon_id": "11372668",
      "name": "会员",
      "font_class": "huiyuan",
      "unicode": "e8b6",
      "unicode_decimal": 59574
    },
    {
      "icon_id": "11372671",
      "name": "减少",
      "font_class": "jianshao",
      "unicode": "e8b7",
      "unicode_decimal": 59575
    },
    {
      "icon_id": "11372677",
      "name": "男",
      "font_class": "nan",
      "unicode": "e8b8",
      "unicode_decimal": 59576
    },
    {
      "icon_id": "11372678",
      "name": "女",
      "font_class": "nv",
      "unicode": "e8b9",
      "unicode_decimal": 59577
    },
    {
      "icon_id": "11372685",
      "name": "扫一扫",
      "font_class": "saoyisao",
      "unicode": "e8ba",
      "unicode_decimal": 59578
    },
    {
      "icon_id": "11372686",
      "name": "日历",
      "font_class": "rili",
      "unicode": "e8bb",
      "unicode_decimal": 59579
    },
    {
      "icon_id": "11372687",
      "name": "评论",
      "font_class": "pinglun",
      "unicode": "e8bc",
      "unicode_decimal": 59580
    },
    {
      "icon_id": "11372690",
      "name": "闪电",
      "font_class": "shandian",
      "unicode": "e8bd",
      "unicode_decimal": 59581
    },
    {
      "icon_id": "11372693",
      "name": "删除",
      "font_class": "shanchu",
      "unicode": "e8be",
      "unicode_decimal": 59582
    },
    {
      "icon_id": "11372694",
      "name": "设置",
      "font_class": "shezhi",
      "unicode": "e8bf",
      "unicode_decimal": 59583
    },
    {
      "icon_id": "11372696",
      "name": "社区",
      "font_class": "shequ",
      "unicode": "e8c0",
      "unicode_decimal": 59584
    },
    {
      "icon_id": "11372698",
      "name": "失败",
      "font_class": "shibai",
      "unicode": "e8c1",
      "unicode_decimal": 59585
    },
    {
      "icon_id": "11372701",
      "name": "收藏",
      "font_class": "shoucang",
      "unicode": "e8c2",
      "unicode_decimal": 59586
    },
    {
      "icon_id": "11372703",
      "name": "首页",
      "font_class": "shouye",
      "unicode": "e8c3",
      "unicode_decimal": 59587
    },
    {
      "icon_id": "11372705",
      "name": "刷新",
      "font_class": "shuaxin",
      "unicode": "e8c4",
      "unicode_decimal": 59588
    },
    {
      "icon_id": "11372711",
      "name": "图片",
      "font_class": "tupian",
      "unicode": "e8c5",
      "unicode_decimal": 59589
    },
    {
      "icon_id": "11372713",
      "name": "未选中",
      "font_class": "weixuanzhong",
      "unicode": "e8c6",
      "unicode_decimal": 59590
    },
    {
      "icon_id": "11372718",
      "name": "我的关注",
      "font_class": "wodeguanzhu",
      "unicode": "e8c7",
      "unicode_decimal": 59591
    },
    {
      "icon_id": "11372726",
      "name": "消息中心",
      "font_class": "xiaoxizhongxin",
      "unicode": "e8c8",
      "unicode_decimal": 59592
    },
    {
      "icon_id": "11372728",
      "name": "眼睛",
      "font_class": "yanjing",
      "unicode": "e8c9",
      "unicode_decimal": 59593
    },
    {
      "icon_id": "11372735",
      "name": "增加",
      "font_class": "zengjia",
      "unicode": "e8ca",
      "unicode_decimal": 59594
    },
    {
      "icon_id": "11487977",
      "name": "arrow-right",
      "font_class": "arrow-right",
      "unicode": "e743",
      "unicode_decimal": 59203
    },
    {
      "icon_id": "11487978",
      "name": "arrow-left",
      "font_class": "arrow-left",
      "unicode": "e744",
      "unicode_decimal": 59204
    },
    {
      "icon_id": "11487981",
      "name": "all",
      "font_class": "all",
      "unicode": "e745",
      "unicode_decimal": 59205
    },
    {
      "icon_id": "11487995",
      "name": "cart- full",
      "font_class": "cart-full",
      "unicode": "e746",
      "unicode_decimal": 59206
    },
    {
      "icon_id": "11488080",
      "name": "map",
      "font_class": "map",
      "unicode": "e758",
      "unicode_decimal": 59224
    },
    {
      "icon_id": "11488168",
      "name": "set",
      "font_class": "set",
      "unicode": "e76c",
      "unicode_decimal": 59244
    },
    {
      "icon_id": "11488175",
      "name": "sport",
      "font_class": "sport",
      "unicode": "e76e",
      "unicode_decimal": 59246
    },
    {
      "icon_id": "15838429",
      "name": "arrow-down",
      "font_class": "arrow-down",
      "unicode": "e665",
      "unicode_decimal": 58981
    }
  ]
}
